fontespass_passwordgenerator/__init__.py
fontespass_passwordgenerator/generate_password.py
fontespass_passwordgenerator-0.0.1.dist-info/METADATA
fontespass_passwordgenerator-0.0.1.dist-info/WHEEL
fontespass_passwordgenerator-0.0.1.dist-info/top_level.txt
fontespass_passwordgenerator-0.0.1.dist-info/RECORD
