Metadata-Version: 2.1
Name: fontespass-passwordgenerator
Version: 0.0.1
Summary: The fontespass_passwordgenerator package is designed to provide functionality for generating secure passwords.
Home-page: https://github.com/dev-marciofontes
Author: Marcio Fontes
Author-email: devfontesmarcio@gmail.com
License: UNKNOWN
Platform: UNKNOWN
Requires-Python: >=3.8
